pyxu_xrt/__init__.py
pyxu_xrt/operator/__init__.py
pyxu_xrt/operator/_drjit.py
pyxu_xrt/operator/ray.py
pyxu_xrt-0.7.dist-info/METADATA
pyxu_xrt-0.7.dist-info/WHEEL
pyxu_xrt-0.7.dist-info/entry_points.txt
pyxu_xrt-0.7.dist-info/licenses/LICENSE
pyxu_xrt-0.7.dist-info/RECORD
