Metadata-Version: 2.3
Name: pyxu_xrt
Version: 0.7
Summary: Pyxu X-Ray Transform Operators.
Project-URL: download, https://github.com/pyxu-org/pyxu_xrt
Author-email: "S. Kashani" <sepand@kashani.ch>
License-Expression: MIT
License-File: LICENSE
Classifier: Development Status :: 4 - Beta
Classifier: Framework :: Pycsou
Classifier: Intended Audience :: Science/Research
Classifier: License :: OSI Approved :: MIT License
Classifier: Programming Language :: Python :: 3.10
Classifier: Programming Language :: Python :: 3.11
Classifier: Programming Language :: Python :: 3.12
Classifier: Programming Language :: Python :: Implementation :: CPython
Classifier: Topic :: Scientific/Engineering
Requires-Python: <3.13,>=3.10
Requires-Dist: drjit==0.4.6
Requires-Dist: pyxu
Provides-Extra: dev
Requires-Dist: pyxu[dev]; extra == 'dev'
